PySock/Sclient.py
PySock/Sserver.py
PySock/__init__.py
PySock/client.py
PySock/server.py
PySock-0.3.2.dist-info/METADATA
PySock-0.3.2.dist-info/WHEEL
PySock-0.3.2.dist-info/top_level.txt
PySock-0.3.2.dist-info/RECORD
