Metadata-Version: 2.1
Name: PySock
Version: 0.3.2
Summary: Pyckage for creating high level multi-client server with E2E encryption.
Home-page: https://github.com/ShikharY10/PySock
Author: Shikhar Yadav
Author-email: <yshikharfzd10@gmail.com>
License: UNKNOWN
Project-URL: Github, https://github.com/ShikharY10/PySock
Project-URL: Shikhar Yadav, https://github.com/ShikharY10
Keywords: socket,tcp,stream,encrypted,E2E,multi-client-server
Platform: UNKNOWN
Classifier: License :: OSI Approved :: MIT License
Classifier: Development Status :: 4 - Beta
Classifier: Intended Audience :: Developers
Classifier: Programming Language :: Python :: 3
Classifier: Operating System :: Unix
Classifier: Operating System :: Microsoft :: Windows
Requires-Dist: PyYAML
Requires-Dist: cryptography
